<annotation>
	<folder>images</folder>
	<filename>1_frame0009.jpg</filename>
	<path>/home/clement/catkin_ws/src/suturo_manipulation/tensorflow_object_detector/train/images/1_frame0009.jpg</path>
	<source>
		<database>Unknown</database>
	</source>
	<size>
		<width>640</width>
		<height>640</height>
		<depth>3</depth>
	</size>
	<segmented>0</segmented>
	<object>
		<name>chipsdose_gelb</name>
		<pose>Unspecified</pose>
		<truncated>1</truncated>
		<difficult>0</difficult>
		<bndbox>
			<xmin>211</xmin>
			<ymin>1</ymin>
			<xmax>519</xmax>
			<ymax>497</ymax>
		</bndbox>
	</object>
</annotation>
